dioxus_widget/__init__.py
dioxus_widget-0.0.5.dist-info/LICENSE
dioxus_widget-0.0.5.dist-info/METADATA
dioxus_widget-0.0.5.dist-info/WHEEL
dioxus_widget-0.0.5.dist-info/top_level.txt
dioxus_widget-0.0.5.dist-info/RECORD
