Metadata-Version: 2.1
Name: dioxus_widget
Version: 0.0.5
Author-email: Jochem Hölscher <a.fake@e.mail>
Project-URL: homepage, https://github.com/JJJHolscher/jupyter-and-dioxus
Classifier: Programming Language :: Python :: 3
Classifier: License :: OSI Approved :: MIT License
Classifier: Operating System :: OS Independent
Requires-Python: >=3.11
License-File: LICENSE
Requires-Dist: ipywidgets
Requires-Dist: jupyter-ui-poll
